lavalamp/__init__.py
lavalamp/plot.py
lavalamp-0.1.0.dist-info/licenses/LICENSE
lavalamp-0.1.0.dist-info/METADATA
lavalamp-0.1.0.dist-info/WHEEL
lavalamp-0.1.0.dist-info/top_level.txt
lavalamp-0.1.0.dist-info/RECORD
