Metadata-Version: 2.4
Name: lavalamp
Version: 0.1.0
Summary: A library for teaching the snake to digest random numbers.
Author-email: Alexandru Sterpu <alex@alstengineering.com>
License: MIT
Keywords: random numbers,monte carlo
Classifier: Programming Language :: Python :: 3
Classifier: License :: OSI Approved :: MIT License
Requires-Python: >=3.9
License-File: LICENSE
Requires-Dist: numpy>=2.0.0
Requires-Dist: matplotlib>=3.6.0
Dynamic: license-file
